<?xml version="1.0" encoding="utf-8"?>
<resources>

	<!-- Main -->
	<string name="v1_app_name">Brother iPrint&amp;Scan</string>
	<string name="v1_launcher_name">iPrint&amp;Scan</string>
	<string name="v1_main_printPictureButton">Foto</string>
	<string name="v1_main_scanButton">Scannen</string>
	<string name="v1_main_docButton">Dokumente</string>
	<string name="v1_main_cloudStorageButton">Cloud-Dienste</string>
	<string name="v1_main_webButton">Webseite</string>
	<string name="v1_main_emailButton">E-Mail</string>
	<string name="v1_main_mapButton">Map</string>
	<string name="v1_main_menu_about">Informationen</string>
	<string name="v1_main_printButton">Drucken</string>

	<!-- NFC -->
	<string name="v1_nfc_guidance_upper">Mithilfe von NFC können Sie ganz einfach über das vor Ihnen stehende Gerät drucken oder scannen.  (Bitte vorab NFC am Android-Gerät einschalten.)</string>
	<string name="v1_nfc_guidance_lower_p1">Suchen Sie diese Markierung an Ihrem Gerät.</string>
	<string name="v1_nfc_guidance_lower_p2">Bereiten Sie Ihr Dokument in iPrint&amp;Scan für das Drucken oder Scannen vor.</string>
	<string name="v1_nfc_guidance_lower_p5">Wählen Sie in den Einstellen NFC-Drucker / NFC-Scanner und drücken Sie \&quot;Zurück\&quot;.</string>
	<string name="v1_nfc_guidance_lower_p3">Halten Sie Ihr Gerät über die Markierung und tippen Sie auf den Bildschirm.</string>
	<string name="v1_nfc_guidance_lower_p4">Das Gerät beginnt automatisch mit dem Ausdrucken oder Scannen.</string>

	<!-- Information -->
	<string name="v1_activity_info">Informationen</string>
	<string name="v1_activity_about">Info zu Brother iPrint&amp;Scan</string>
	<string name="v1_about_copy_right">©2010-2017 Brother Industries, Ltd.\nAll Rights Reserved.</string>
	<string name="v1_about_application_name">iPrint&amp;Scan</string>
	<string name="v1_about_ok_button">Fertig</string>
	<string name="v1_info_item_label_about">Info</string>
	<string name="v1_info_nfc_btn">NFC</string>
	<string name="v1_info_support_btn">Support</string>
	<string name="v1_info_appname_btn">Brother iPrint&amp;Scan</string>
	<string name="v1_info_usage_btn">Nutzungsinformationen</string>
	<string name="v1_info_item_label_account">Konto</string>
	<string name="v1_info_item_label_account_settings">Kontoeinstellungen</string>
	<string name="v1_google_name">Google</string>
	<string name="v1_dropbox_name">Dropbox</string>
	<string name="v1_onedrive_name">OneDrive</string>
	<string name="v1_evernote_name">Evernote</string>
	<string name="v1_activity_usage_info">Nutzungsinformationen</string>
	<string name="v1_activity_google_account">Konto</string>
	<string name="v1_google_account_list_explain">Sie müssen sich bei Ihrem Google-Konto anmelden, um über Google Drive drucken und die Remote- und E-Mail-Druckfunktionen nutzen zu können.  Die Remote-Druckfunktion verwendet Google Cloud Print und ermöglicht Ihnen das Drucken von jedem beliebigen Ort aus.</string>
	<string name="v1_cloud_msg_sign_in">Sie müssen sich bei Ihrem %1$s-Konto anmelden, um von %2$s zu drucken.</string>
	<string name="v1_cloud_msg_sign_out">Wenn Sie sich abmelden, können Sie nicht von %s aus drucken.</string>
	<string name="v1_account_item_label_select_account">Konto wählen</string>
	<string name="v1_info_item_label_no_account">Konto ist nicht registriert</string>
	<string name="v1_cloud_btn_sign_in">Anmelden</string>
	<string name="v1_cloud_btn_sign_out">Abmelden</string>
	<string name="v1_info_item_label_cloud_services">Cloud-Dienste</string>
	<string name="v1_info_item_label_license">Lizenz</string>
	<string name="v1_info_item_label_other_app">Andere Brother-Apps</string>
	<string name="v1_info_item_label_nenga_print">年賀状プリント</string>
	<string name="v1_info_item_label_map_print">地図プリント</string>

	<!-- JPEG Filer -->
	<string name="v1_activity_filer">Foto auswählen</string>
	<string name="v1_ifiler_noimages">Keine Fotos gefunden</string>

	<!-- Print Share -->
	<string name="v1_print_share_name">Brother iPrint&amp;Scan</string>
	<string name="v1_generic_msg_processing_now">Verarbeitung...</string>

	<!-- Document Filer -->
	<string name="v1_activity_doc_select">Dokumentenauswahl</string>
	<string name="v1_cloudprint_selectfile_nodoc">Kein Dokument gefunden</string>
	<string name="v1_activity_sheet_select">Blattauswahl</string>
	<string name="v1_file_size_KB">KB</string>

	<!-- Cloud Storage -->
	<string name="v1_activity_cloud_storage_select">Cloud-Dienste</string>
	<string name="v1_cloud_msg_downloading">Herunterladen von %s...</string>
	<string name="v1_cloud_item_label_share_folder">freigegeben</string>
	<string name="v1_cloud_msg_nodata">Keine unterstützten Dateien gefunden.</string>
	<string name="v1_generic_msg_search_in_this_service">In %s suchen</string>
	<string name="v1_generic_msg_search_in_this_folder">In diesem Ordner suchen</string>
	<string name="v1_generic_msg_search">Suchen</string>
	<string name="v1_generic_msg_no_matches">Keine Übereinst. gefunden</string>
	<string name="v1_google_drive_name">Google Drive</string>
	<string name="v1_cloud_msg_nonote">Keine Notiz gefunden</string>
	<string name="v1_cloud_msg_seach_in_this_notebook">Suche in diesem Notizbuch</string>

	<!-- Text Print -->
	<string name="v1_print_btn_web_print">Webseitendruck</string>
	<string name="v1_print_btn_text_print">Textdruck</string>
	<string name="v1_print_item_label_select_url">URL wählen</string>
	<string name="v1_textprint_email_from">Von:</string>
	<string name="v1_textprint_email_date_tx">Gesendet:</string>
	<string name="v1_textprint_email_date_rx">Empfangen:</string>
	<string name="v1_textprint_email_to">An:</string>
	<string name="v1_textprint_email_cc">Cc:</string>
	<string name="v1_textprint_email_bcc">Bcc:</string>

	<!-- Browser -->
	<string name="v1_browser_btn_print_preview">Druckvorschau</string>
	<string name="v1_browser_menu_back">Zurück</string>
	<string name="v1_browser_menu_forward">Vor</string>
	<string name="v1_browser_menu_bookmarks">Lesezeichen</string>
	<string name="v1_browser_menu_history">Verlauf</string>
	<string name="v1_browser_item_label_bookmark_current">Lesezeichen hinzu...</string>
	<string name="v1_browser_menu_bookmark_last">Lesezeichen für letzte Seite</string>
	<string name="v1_browser_menu_clear_history">Verlauf löschen</string>
	<string name="v1_browser_nohistory">Browserverlauf ist leer.</string>
	<string name="v1_browser_item_label_edit">Bearbeiten</string>
	<string name="v1_browser_item_label_delete">Löschen</string>
	<string name="v1_browser_item_label_add_bookmark">Lesezeichen hinzu</string>
	<string name="v1_browser_item_label_edit_bookmark">Lesezeichen bearb.</string>
	<string name="v1_browser_item_label_title">Name</string>
	<string name="v1_browser_item_label_url">URL</string>
	<string name="v1_add_bookmark_toast_message">Zu Ihren Lesezeichen hinzugefügt.</string>
	<string name="v1_add_bookmark_toast_button">Lesezeichen bearbeiten</string>
	<string name="v1_delete_bookmark_toast_message_part">%s wurde gelöscht.</string>

	<!-- Email -->
	<string name="v1_email_item_label_label">Etikett</string>
	<string name="v1_email_item_label_account">Konto</string>
	<string name="v1_email_noemail">Keine E-Mail gefunden</string>
	<string name="v1_email_item_label_password">Kennwort</string>
	<string name="v1_email_account_dlg_title">Google-Konto</string>
	<string name="v1_email_item_label_inbox">Posteingang</string>
	<string name="v1_email_item_label_all_mail">All mail</string>

	<!-- Print Preview -->
	<string name="v1_activity_print_preview">Druckvorschau</string>
	<string name="v1_print_btn_print">Drucken</string>
	<string name="v1_generic_btn_Cansel">Abbrechen</string>
	<string name="v1_print_msg_printing_now">Drucken...</string>
	<string name="v1_print_msg_spooling_now">Ausdruck ...(Offline)</string>
	<string name="v1_generic_msg_printer_not_selected">KeinGerät ausgewählt</string>
	<string name="v1_print_msg_canceling_now">Abbrechen...</string>
	<string name="v1_print_msg_settings_changed_for_AP">Abgerufene Druckeinstellungen für diesen Wi-Fi Access Point.</string>
	<string name="v1_print_preview_papersize_id_0">4 Zoll x 6 Zoll</string>
	<string name="v1_print_preview_papersize_id_1">3,5 Zoll x 5 Zoll</string>
	<string name="v1_print_preview_papersize_id_0_cm">10 x 15 cm</string>
	<string name="v1_print_preview_papersize_id_1_cm">9 x 13 cm</string>
	<string name="v1_print_preview_papersize_id_12">5 Zoll x 7 Zoll</string>
	<string name="v1_print_preview_papersize_id_12_cm">13 x 18 cm</string>
	<string name="v1_print_item_label_page">%d Seite</string>
	<string name="v1_print_item_label_pages">%d Seiten</string>
	<string name="v1_generic_msg_checking_device">Gerät wird überprüft ...</string>
	<string name="v1_print_msg_nfc_connected">Druckvorgang wird vorbereitet.  Sie können Ihr Mobilgerät vom Gerät wegbewegen.</string>
	<string name="v1_print_msg_nfc_printing_now">Druckvorgang läuft.  Sie können Ihr Mobilgerät vom Gerät wegbewegen.</string>
	<string name="v1_print_menu_select_all">Alle auswählen</string>
	<string name="v1_print_menu_deselect_all">Auswahl aufheben</string>
	<string name="v1_generic_msg_nfc_on_operate">Gerät über NFC-Markierung halten, auf Bildschirm tippen.</string>
	<string name="v1_generic_msg_nfc_off_operate">Schalten Sie vorab NFC am Android-Gerät ein.\n</string>
	<string name="v1_print_item_label_nfc_printer">NFC-Drucker</string>

	<!-- Document Preview -->
	<string name="v1_print_btn_current_1p_print">Dies drucken</string>
	<string name="v1_print_btn_all_print">Alles druck.</string>
	<string name="v1_print_msg_server_connecting">Datei wird auf Server verarbeitet.</string>

	<!-- Print Settings -->
	<string name="v1_activity_print_settings">Druckeinstellungen</string>
	<string name="v1_print_item_label_printer">Drucker</string>
	<string name="v1_print_item_label_options">Druckoptionen</string>
	<string name="v1_print_item_label_papersize">Papiergröße</string>
	<string name="v1_print_item_label_media">Druckmedium</string>
	<string name="v1_print_item_label_copies">Kopien</string>
	<string name="v1_print_item_label_colortype">Farbe/Schwarzweiß</string>
	<string name="v1_print_item_label_dupulex">Beidseitig</string>
	<string name="v1_generic_msg_printer_search_now">Suche...</string>
	<string name="v1_print_item_label_layout">Layout</string>
	<string name="v1_activity_find_printer">Drucker</string>
	<string name="v1_print_papersize_id_0">4 Zoll x 6 Zoll (10 x 15 cm)</string>
	<string name="v1_print_papersize_id_1">3,5 Zoll x 5 Zoll (9 x 13 cm)</string>
	<string name="v1_print_papersize_id_2">Letter</string>
	<string name="v1_print_papersize_id_3">A4</string>
	<string name="v1_print_papersize_id_4">Legal</string>
	<string name="v1_print_papersize_id_5">A3</string>
	<string name="v1_print_papersize_id_6">Ledger</string>
	<string name="v1_print_papersize_id_7">B4</string>
	<string name="v1_print_papersize_id_8">Japanese Hagaki</string>
	<string name="v1_print_papersize_id_9">B5</string>
	<string name="v1_print_papersize_id_0_cm">10 x 15 cm (4 Zoll x 6 Zoll)</string>
	<string name="v1_print_papersize_id_1_cm">9 x 13 cm (3,5 Zoll x 5 Zoll)</string>
	<string name="v1_print_papersize_id_12">5 Zoll x 7 Zoll (13 x 18 cm)</string>
	<string name="v1_print_papersize_id_12_cm">13 x 18 cm (5 Zoll x 7 Zoll)</string>
	<string name="v1_print_media_id_0">Glanzpapier</string>
	<string name="v1_print_media_id_1">Normalpapier</string>
	<string name="v1_print_media_id_2">Inkjet Paper</string>
	<string name="v1_print_color_id_0">Farbe</string>
	<string name="v1_print_color_id_1">Schwarzweiß</string>
	<string name="v1_print_duplex_id_0">AUS</string>
	<string name="v1_print_duplex_id_1">An langer Kante spiegeln</string>
	<string name="v1_print_duplex_id_2">An kurzer Kante spiegeln</string>
	<string name="v1_print_layout_id_0">1 auf 1</string>
	<string name="v1_print_layout_id_1">2 auf 1</string>
	<string name="v1_print_layout_id_2">4 auf 1</string>
	<string name="v1_print_item_label_density">Druckdichte</string>
	<string name="v1_print_item_label_feedmode">Bandvorschubmodus</string>
	<string name="v1_print_item_label_bluetooth_printer">Bluetooth-Drucker</string>
	<string name="v1_print_item_label_add_printer">Drucker hinzufügen</string>
	<string name="v1_print_item_label_density_bar">Leiste verschieben, um die Druckdichte zu wählen.</string>
	<string name="v1_print_item_label_feedmode_id_0">Kein Bandvorschub (Rollenpapier)</string>
	<string name="v1_print_item_label_feedmode_id_1">Bandvorsch S.größ fest (Rollenpap.)</string>
	<string name="v1_print_item_label_feedmode_id_2">1Seitenbandvorschub (Pap. schneiden)</string>
	<string name="v1_print_item_label_feedmode_id_3">1S.bandvorschub (mark.Rollenpap.)</string>
	<string name="v1_print_item_label_borderless">Randlos drucken</string>
	<string name="v1_print_borderless_id_0">EIN</string>
	<string name="v1_print_borderless_id_1">AUS</string>
	<string name="v1_print_item_label_doc_options">Dokumentenoptionen</string>
	<string name="v1_print_item_label_scaling">Skalierung</string>
	<string name="v1_print_scaling_id_0">Original-Skalierung verwenden</string>
	<string name="v1_print_scaling_id_1">Keine Skalierung</string>
	<string name="v1_print_scaling_id_2">Anpassen für 1 Seite</string>
	<string name="v1_print_scaling_id_3">Anpassen für 1 Seite, breit</string>
	<string name="v1_print_scaling_id_4">Anpassen für 1 Seite, hoch</string>
	<string name="v1_print_item_label_orientation">Ausrichtung</string>
	<string name="v1_print_orientation_id_0">Hochformat</string>
	<string name="v1_print_orientation_id_1">Querformat</string>
	<string name="v1_print_item_label_gcp_printer">Remote-Drucker</string>
	<string name="v1_print_item_label_wifi_printer">Netzwerkdrucker</string>
	<string name="v1_print_item_label_print_quality">Qualität</string>
	<string name="v1_print_quality_id_0">Normal</string>
	<string name="v1_print_quality_id_1">Fein</string>
	<string name="v1_widi_msg_connecting">Verbinden über Wi-Fi Direct.  Führen Sie die angezeigten Anweisungen aus, um das ausgewählte Gerät zu zertifizieren.</string>
	<string name="v1_widi_msg_connected">Das ausgewählte Gerät wurde über Wi-Fi Direct verbunden.</string>
	<string name="v1_generic_btn_manual">Manuell einstellen</string>
	<string name="v1_generic_item_label_IP">IP-Adresse</string>
	<string name="v1_generic_btn_connect">Verbinden</string>

	<!-- Scan Main -->
	<string name="v1_activity_scan_main">Scannen</string>
	<string name="v1_scan_btn_scan">Scannen</string>
	<string name="v1_scan_msg_settings_changed_for_AP">Abgerufene Scaneinstellungen für diesen Wi-Fi Access Point.</string>
	<string name="v1_scan_main_papersize_id_46">4 Zoll x 6 Zoll</string>
	<string name="v1_scan_main_papersize_id_PhotoL">3,5 Zoll x 5 Zoll</string>
	<string name="v1_scan_main_papersize_id_Card">2,4 Zoll x 3,5 Zoll</string>
	<string name="v1_scan_main_papersize_id_46_cm">10 x 15 cm</string>
	<string name="v1_scan_main_papersize_id_PhotoL_cm">9 x 13 cm</string>
	<string name="v1_scan_main_papersize_id_Card_cm">60 x 90 mm</string>
	<string name="v1_scan_msg_nfc_connected">Scanvorgang wird vorbereitet.  Sie können Ihr Mobilgerät vom Gerät wegbewegen.</string>
	<string name="v1_scan_msg_nfc_scanning_now">Scanvorgang läuft.  Sie können Ihr Mobilgerät vom Gerät wegbewegen.</string>
	<string name="v1_scan_item_label_nfc_scanner">NFC-Scanner</string>

	<!-- Scan Settings -->
	<string name="v1_activity_scan_settings">Scaneinstellungen</string>
	<string name="v1_scan_item_label_scanner">Scanner</string>
	<string name="v1_scan_item_label_options">Scanoptionen</string>
	<string name="v1_scan_papersize">Dokumentengröße</string>
	<string name="v1_scan_scantype">Scanmodus</string>
	<string name="v1_scan_msg_scanning_now">Scannen...</string>
	<string name="v1_scan_msg_scanning_page">%d Seite(n)</string>
	<string name="v1_scan_duplextype">Beidseitig</string>
	<string name="v1_activity_find_scanner">Scanner</string>
	<string name="v1_scan_papersize_id_AUTO">Auto</string>
	<string name="v1_scan_papersize_id_A4">A4</string>
	<string name="v1_scan_papersize_id_Letter">Letter</string>
	<string name="v1_scan_papersize_id_46">4 Zoll x 6 Zoll (10 x 15 cm)</string>
	<string name="v1_scan_papersize_id_PhotoL">3,5 Zoll x 5 Zoll (9 x 13 cm)</string>
	<string name="v1_scan_papersize_id_Card">2,4 Zoll x 3,5 Zoll (60 x 90 mm)</string>
	<string name="v1_scan_papersize_id_Legal">Legal</string>
	<string name="v1_scan_papersize_id_A3">A3</string>
	<string name="v1_scan_papersize_id_Ledger">Ledger</string>
	<string name="v1_scan_papersize_id_B4">B4</string>
	<string name="v1_scan_papersize_id_B5">B5</string>
	<string name="v1_scan_papersize_id_46_cm">10 x 15 cm (4 Zoll x 6 Zoll)</string>
	<string name="v1_scan_papersize_id_PhotoL_cm">9 x 13 cm (3,5 Zoll x 5 Zoll)</string>
	<string name="v1_scan_papersize_id_Card_cm">60 x 90 mm (2,4 Zoll x 3,5 Zoll)</string>
	<string name="v1_scan_scantype_id_Color">Farbe</string>
	<string name="v1_scan_scantype_id_ColorFast">Farbe (schnell)</string>
	<string name="v1_scan_scantype_id_BW">Schwarzweiß</string>
	<string name="v1_scan_duplextype_id_Simplex">AUS</string>
	<string name="v1_scan_duplextype_id_DuplexLONGEDGE">An langer Kante spiegeln</string>
	<string name="v1_scan_duplextype_id_DuplexSHORTEDGE">An kurzer Kante spiegeln</string>

	<!-- Scanned Image -->
	<string name="v1_activity_scanned_image">Gescanntes Bild</string>
	<string name="v1_scan_btn_save">Speichern</string>
	<string name="v1_generic_msg_scan_save_select_format">Auf Karte speichern</string>
	<string name="v1_scan_Save_Format_JPEG">Als JPEG speichern</string>
	<string name="v1_scan_Save_Format_PDF">Als PDF speichern</string>
	<string name="v1_scan_msg_jpeg_saving_now">Speichern als JPEG...</string>
	<string name="v1_scan_msg_pdf_saving_now">Speichern als PDF...</string>
	<string name="v1_scan_share_type_dlg_title">Freigabetyp</string>
	<string name="v1_scan_share_JPEG">Als JPEG freigeben</string>
	<string name="v1_scan_share_PDF">Als PDF freigeben</string>
	<string name="v1_scan_share_JPEG_dlg_title">Als JPEG freig. über</string>
	<string name="v1_scan_share_PDF_dlg_title">Als PDF freig. über</string>

	<!-- Crop Image -->
	<string name="v1_crop_btn_crop">Zuschn.</string>
	<string name="v1_crop__menu_rotate_right">N. re. dreh.</string>
	<string name="v1_crop__menu_rotate_left">N. li. dreh.</string>

	<!-- Error -->
	<string name="v1_error_wifi_title">Wi-Fi-Setup-Fehler</string>
	<string name="v1_error_wifi_msg">Wi-Fi ist deaktiviert oder nicht verbunden.\nMöchten Sie mit dem Wi-Fi-Setup beginnen?</string>
	<string name="v1_generic_btn_OK">OK</string>
	<string name="v1_generic_btn_continue">Fortfahren</string>
	<string name="v1_error_no_device_title">Keine unterstützten Geräte gefunden</string>
	<string name="v1_error_connect_title">Verbinden nicht möglich</string>
	<string name="v1_error_connect_wifi_off_msg">Bestätigen Sie Folgendes:\n-Wi-Fi ist deaktiviert oder nicht verbunden.\n-Schalten Sie Ihr Gerät aus wieder ein und versuchen Sie es dann erneut.</string>
	<string name="v1_error_connect_header_msg">Bestätigen Sie Folgendes:\n- Überprüfen Sie, ob das Gerät und das Android-Gerät mit dem gleichen WLAN-Netzwerk verbunden sind.\n</string>
	<string name="v1_error_connect_ssid_msg">  SSID Ihres Android-Geräts:%s\n\n</string>
	<string name="v1_error_connect_footer_msg">- Prüfen Sie, ob die Funktion \&quot;Privacy Separator\&quot; Ihres Wireless Access Points/Routers deaktiviert ist.\n-Schalten Sie Ihr Gerät aus wieder ein und versuchen Sie es dann erneut.\nVergewissern Sie sich, dass WLAN aktiviert und Ihr Gerät verbunden ist.\n\nSollte das Problem weiterhin bestehen: Tippen Sie auf „Manuell einstellen“ und geben Sie die IP-Adresse des Geräts ein. Die IP-Adresse finden Sie im Netzwerkmenü Ihres Geräts.</string>
	<string name="v1_error_connect_nfc_msg">\n-Wenn Ihr Brother-Gerät NFC unterstützt, können Sie drucken oder scannen, indem Sie Ihr Android-Gerät neben das NFC-Logo halten und auf das Bild tippen. Tippen Sie auf das Informationsmenü, um weitere Information zu NFC zu erhalten.</string>
	<string name="v1_generic_btn_settings">Einstellungen</string>
	<string name="v1_error_no_disk_title">Keine Speicherkarte gefunden</string>
	<string name="v1_error_no_disk_msg">Setzen Sie eine Speicherkarte ein.</string>
	<string name="v1_error_internal_title">Interner Fehler</string>
	<string name="v1_error_internal_msg">Fortfahren nicht möglich.</string>
	<string name="v1_error_web_extended_title">Interner Fehler</string>
	<string name="v1_error_web_extended_msg">Fortfahren nicht möglich.</string>
	<string name="v1_error_disk_full_title">Speicherkarte voll</string>
	<string name="v1_error_disk_full_msg">Geben Sie Speicherplatz auf der Karte durch Löschen nicht mehr benötigter Dateien frei.</string>
	<string name="v1_error_scandocjam_title">Stau der Scandokumente</string>
	<string name="v1_error_scandocjam_msg">Öffnen Sie die Abdeckung des Vorlageneinzugs und entfernen Sie das gestaute Papier. Wiederholen Sie den Vorgang.</string>
	<string name="v1_error_scannodoc_title">Fehler Dokumentenscan</string>
	<string name="v1_error_scannodoc_msg">Im automatischen Vorlageneinzug (ADF) wurde kein Dokument erkannt. Legen Sie ein Dokument in den Vorlageneinzug und versuchen Sie es erneut.</string>
	<string name="v1_error_scantimeout_title">Zeitüberschreitung</string>
	<string name="v1_error_scantimeout_msg">Zeitüberschreitung bei der Datenübertragung.</string>
	<string name="v1_error_scancvropen_title">Abdeckung geöffnet</string>
	<string name="v1_error_scancvropen_msg">Die Abdeckung ist geöffnet.  Schließen Sie die Abdeckung und wiederholen Sie den Vorgang.</string>
	<string name="v1_error_scandevbusy_title">Gerät beschäftigt</string>
	<string name="v1_error_scandevbusy_msg">Wiederholen Sie den Vorgang, nachdem die aktuelle Funktion abgeschlossen wurde.</string>
	<string name="v1_error_scandevmemful_title">Gerätespeicher voll</string>
	<string name="v1_error_scandevmemful_msg">Wenn sich noch Aufträge im Gerätespeicher befinden, warten Sie, bis diese Aufträge abgeschlossen wurden, oder löschen Sie anstehende Aufträge. Wiederholen Sie den Vorgang.</string>
	<string name="v1_error_shared_format_title">Datenformatfehler</string>
	<string name="v1_error_shared_format_msg">Es können nur Webseiten freigegeben werden.</string>
	<string name="v1_error_scanned_image_not_saved_title">Das gescannte Bild wurde nicht gespeichert</string>
	<string name="v1_error_scanned_image_not_saved_msg">Das Bild wird gelöscht, wenn Sie fortfahren.  Möchten Sie fortfahren?</string>
	<string name="v1_error_previewed_image_not_printed_title">Das in der Vorschau gez. Bild wurde nicht gedruckt</string>
	<string name="v1_error_previewed_image_not_printed_msg">Das Bild wird gelöscht, wenn Sie fortfahren.  Möchten Sie fortfahren?</string>
	<string name="v1_error_printer_status_title">Druckfehler</string>
	<string name="v1_error_printer_status_msg">Verbindung zum Gerät kann nicht hergestellt werden.  Überprüfen Sie den Gerätestatus.\n\nMöchten Sie mit dem Drucken fortfahren?</string>
	<string name="v1_error_print_cancel_title">Druck abbrechen</string>
	<string name="v1_error_print_cancel_msg">Keine Antwort.  Brother iPrint&amp;Scan wird beendet.</string>
	<string name="v1_error_scanfailed_title">Scan fehlgeschlagen</string>
	<string name="v1_error_scanwritefailed_title">Schreibfehler gescanntes Bild</string>
	<string name="v1_error_scanwritefailed_msg">Gescanntes Bild kann nicht gespeichert werden. Bitte überprüfen Sie, dass eine Speicherkarte eingesetzt ist.</string>
	<string name="v1_error_scanautoduplexsize_title">Fehler Duplex-Format</string>
	<string name="v1_error_scanautoduplexsize_msg">Duplexscannen kann nur für Dok. bis zum Format A4 verw. werden. Brechen Sie bitte das Duplexscannen ab oder ändern Sie die Einst. für die Dok.größe in der Anwend.</string>
	<string name="v1_error_doc_not_supported_format_title">Nicht unterstütztes Dokument</string>
	<string name="v1_error_doc_not_supported_format_msg">Dateiformat wird nicht unterstützt.</string>
	<string name="v1_error_doc_cannot_open_title">Fehler beim Drucken des Dokumentes</string>
	<string name="v1_error_doc_cannot_open_msg">Dieses Dokument kann nicht geöffnet werden.</string>
	<string name="v1_error_doc_size_title">Fehler bei Dokumentengröße</string>
	<string name="v1_error_doc_size_msg">Datei ist zu groß.</string>
	<string name="v1_error_doc_too_large_msg">Datei ist zu groß.\nBei diesem Dateityp kann ein Dokument kleiner als %s gedruckt werden.</string>
	<string name="v1_error_doc_too_many_pages_msg">Datei ist zu groß.\nBei diesem Dateityp kann ein Dokument kleiner als %d Seiten gedruckt werden.</string>
	<string name="v1_error_doc_server_down_title">Zugriffsfehler Server</string>
	<string name="v1_error_doc_server_down_msg">Dienst vorübergehend nicht verfügbar. Versuchen Sie es später erneut.</string>
	<string name="v1_error_doc_server_internal_title">Interner Fehler Server</string>
	<string name="v1_error_doc_server_internal_msg">Fortfahren nicht möglich.</string>
	<string name="v1_error_doc_func_not_available_title">Fehler beim Drucken des Dokumentes</string>
	<string name="v1_error_doc_func_not_available_msg">Diese Funktion ist in Ihrer Region nicht verfügbar.</string>
	<string name="v1_error_doc_fail_page_title">Fehler bei der Dokumentenvorschau</string>
	<string name="v1_error_doc_fail_page_msg">Vorschau der Seiten unten fehlgeschlagen.\n\nSeite:</string>
	<string name="v1_error_doc_process_running_title">Brother iPrint&amp;Scan läuft bereits</string>
	<string name="v1_error_doc_process_running_msg">Tippen Sie auf OK, um zu iPrint&amp;Scan zu gehen und warten Sie dann, bis der aktuelle Druckauftrag beendet ist, bevor Sie es erneut versuchen.</string>
	<string name="v1_error_browser_clear_history_title">Verlauf löschen</string>
	<string name="v1_error_browser_clear_all_history_msg">Möchten Sie wirklich alle Einträge in der Verlaufsliste löschen</string>
	<string name="v1_error_browser_clear_this_history_msg">Möchten Sie diesen Verlauf wirklich löschen?</string>
	<string name="v1_error_browser_delete_bookmark_title">Löschen</string>
	<string name="v1_error_browser_delete_bookmark_msg">Möchten Sie dieses Lesezeichen wirklich löschen?</string>
	<string name="v1_error_browser_no_name_title">Title is Not Entered</string>
	<string name="v1_error_browser_no_name_msg">Enter title.</string>
	<string name="v1_error_email_cannot_connect_title">Verbinden nicht möglich</string>
	<string name="v1_error_email_cannot_connect_msg">Ihr E-Mail-Konto ist ungültig oder nicht korrekt.\nBitte überprüfen Sie Ihre Anmeldedaten.</string>
	<string name="v1_error_email_cannot_retrieve_mail_title">Zugriffsfehler Server</string>
	<string name="v1_error_email_cannot_retrieve_mail_msg">Dienst vorübergehend nicht verfügbar. Versuchen Sie es später erneut.</string>
	<string name="v1_error_email_cannot_retrieve_account_title">Konto nicht registriert</string>
	<string name="v1_error_email_cannot_retrieve_account_msg">Bitte melden Sie sich bei einem Google-Konto an.</string>
	<string name="v1_error_scanadfcvropen_title">Abdeckung geöffnet</string>
	<string name="v1_error_scanadfcvropen_msg">Schließen Sie die Abdeckung des Vorlageneinzugs.</string>
	<string name="v1_error_scandocadftray_title">Scannen nicht möglich</string>
	<string name="v1_error_scandocadftray_msg">Entfernen Sie das Dokument aus dem Ausgabefach des Vorlageneinzugs.</string>
	<string name="v1_error_scanmultifeed_title">Multieinzug erkannt.</string>
	<string name="v1_error_scanmultifeed_msg">Drücken Sie die Stopp-Taste am Gerät, um den Fehler zu beheben.</string>
	<string name="v1_error_no_paper_feed_title">Papier prüfen</string>
	<string name="v1_error_no_paper_feed_msg">Papier einlegen</string>
	<string name="v1_error_bluetooth_cannot_connect_title">Verbinden nicht möglich</string>
	<string name="v1_error_bluetooth_cannot_connect_msg">Wenn das Gerät ausgeschaltet ist, schalten Sie es ein. Stellen Sie außerdem sicher, dass die Netzwerkeinstellungen korrekt konfiguriert sind.</string>
	<string name="v1_error_device_notsupported_or_poweroff_title">Verbinden nicht möglich</string>
	<string name="v1_error_device_notsupported_or_poweroff_msg">Dieses Gerät ist ausgeschaltet oder wird nicht unterstützt.</string>
	<string name="v1_error_bluetooth_title">Bluetooth-Fehler</string>
	<string name="v1_error_bluetooth_msg">Bluetooth ist ausgeschaltet.\nMöchten Sie Bluetooth einschalten?</string>
	<string name="v1_error_bluetooth_printer_status_title">Druckfehler</string>
	<string name="v1_error_bluetooth_printer_status_msg">Überprüfen Sie den Gerätestatus.</string>
	<string name="v1_error_bluetooth_printer_overheat_title">Druckfehler</string>
	<string name="v1_error_bluetooth_printer_overheat_msg">Überprüfen Sie den Gerätestatus.</string>
	<string name="v1_error_email_html_memfull_title">Interner Fehler</string>
	<string name="v1_error_email_html_memfull_msg">Die HTML-E-Mail, die Sie öffnen möchten, ist zu groß. Sie wird nur als einfache Text-E-Mail angezeigt.</string>
	<string name="v1_error_sfl_print_title">Druckfehler</string>
	<string name="v1_error_sfl_print_msg">Klären Sie die Einstellungen der Benutzersperre mit Ihrem Systemadministrator.</string>
	<string name="v1_error_sfl_print_max_title">Druckfehler</string>
	<string name="v1_error_sfl_print_max_msg">Sie haben die maximale Zahl an zulässigen Ausdrucken erreicht. Klären Sie die Einstellungen der Benutzersperre mit Ihrem Systemadministrator.</string>
	<string name="v1_error_ms_print_title">Druckfehler</string>
	<string name="v1_error_ms_print_msg">Klären Sie die Einstellungen der Zugangssperre mit Ihrem Systemadministrator.</string>
	<string name="v1_error_ms_scan_title">Scanfehler</string>
	<string name="v1_error_ms_scan_msg">Klären Sie die Einstellungen der Zugangssperre mit Ihrem Systemadministrator.</string>
	<string name="v1_error_wrong_settings_title">Falsche Einstellungen</string>
	<string name="v1_error_wrong_settings_msg">Die aktuellen Einstellungen werden von Ihrem Brother-Gerät nicht unterstützt. Bestätigen Sie, dass die Einstellungen zu Papiergröße/Dokumentgröße usw. korrekt sind.</string>
	<string name="v1_error_sfl_scan_title">Scanfehler</string>
	<string name="v1_error_sfl_scan_msg">Klären Sie die Einstellungen der Benutzersperre mit Ihrem Systemadministrator.</string>
	<string name="v1_error_scanner_adf_card_tray_open_title">Card Output Tray is Open</string>
	<string name="v1_error_scanner_adf_card_tray_open_msg">To scan documents larger\nthan 4\&quot;x6\&quot;(10x15cm), Please close\nthe Card Output Tray.</string>
	<string name="v1_error_scanner_adf_card_tray_close_title">Card Output Tray is Closed</string>
	<string name="v1_error_scanner_adf_card_tray_close_msg">To scan documents that Photo L and 4\&quot;x6\&quot;(10x15cm), please open the Card Output Tray.</string>
	<string name="v1_error_nfc_print_unable_to_send_title">Senden nicht möglich</string>
	<string name="v1_error_nfc_print_unable_to_send_msg">Die Daten können nicht gesendet werden, da Ihr Android-Gerät zu weit vom NFC-Logo auf dem Gerät entfernt war.\nTippen Sie erneut auf das Logo und halten Sie Ihr Android-Gerät solange neben das NFC-Logo, bis der Druckvorgang startet.</string>
	<string name="v1_error_nfc_scan_unable_to_send_title">Senden nicht möglich</string>
	<string name="v1_error_nfc_scan_unable_to_send_msg">Die Daten können nicht gesendet werden, da Ihr Android-Gerät zu weit vom NFC-Logo auf dem Gerät entfernt war.\nTippen Sie erneut auf das Logo und halten Sie Ihr Android-Gerät solange neben das NFC-Logo, bis der Scanvorgang startet.</string>
	<string name="v1_error_nfc_wifi_direct_cannot_connect_title">Verbinden nicht möglich</string>
	<string name="v1_error_nfc_wifi_direct_cannot_connect_msg">NFC-Verbindung fehlgeschlagen. Schalten Sie Ihr Brother-Gerät aus und wieder ein und versuchen Sie es erneut. Überprüfen Sie außerdem, ob Ihr Android-Gerät vollständig aufgeladen ist.</string>
	<string name="v1_error_nfc_wifi_direct_client_cannot_connect_title">Verbinden nicht möglich</string>
	<string name="v1_error_nfc_wifi_direct_client_cannot_connect_msg">Das Android-Gerät wurde als WiFi Direct Client eingerichtet. Schalten Sie WiFi Direct aus und versuchen Sie es erneut.</string>
	<string name="v1_error_nfc_cannot_connect_title">Verbinden nicht möglich</string>
	<string name="v1_error_nfc_cannot_connect_msg">Versuchen Sie es später erneut.</string>
	<string name="v1_error_nfc_another_device_connected_title">Verbinden nicht möglich</string>
	<string name="v1_error_nfc_another_device_connected_msg">Es ist bereits ein anderes Gerät angeschlossen. Versuchen Sie es später erneut.</string>
	<string name="v1_error_nfc_wrong_operation_title">Bedienungsfehler</string>
	<string name="v1_error_nfc_wrong_operation_msg">Die Verwendung dieser Funktion steht nur auf dem Bildschirm \&quot;Druckvorschau/Scannen\&quot; zur Verfügung. Während der Verarbeitung des Dokuments ist sie nicht verfügbar.</string>
	<string name="v1_error_doc_internet_cannot_connect_title">Keine Internetverbindung</string>
	<string name="v1_error_doc_internet_cannot_connect_msg">Zum Ausdrucken von PDF- und Office-Dateien ist eine Internetverbindung erforderlich. Verbinden Sie Ihr Android-Gerät und das Gerät mit einem WLAN-Netzwerk mit Internetverbindung. </string>
	<string name="v1_error_doc_wifi_direct_title">Verbinden nicht möglich</string>
	<string name="v1_error_doc_wifi_direct_msg">Schalten Sie Wi-Fi Direct AUS und versuchen Sie es erneut.</string>
	<string name="v1_error_scanner_adf_card_disable_title">Document Scan Error</string>
	<string name="v1_error_scanner_adf_card_disable_msg">Unable to scan from the ADF in the document size chosen. Place your document on the scanner glass.</string>
	<string name="v1_error_nfc_print_setting_confirm_title">Kein NFC-Drucker ausgewählt</string>
	<string name="v1_error_nfc_print_setting_confirm_msg">Um über NFC zu drucken, wählen Sie den NFC-Drucker in den Druckeinstellungen. Möchten Sie die Druckeinstellungen anzeigen?</string>
	<string name="v1_error_nfc_scan_setting_confirm_title">Kein NFC-Scanner ausgewählt</string>
	<string name="v1_error_nfc_scan_setting_confirm_msg">Um über NFC zu scannen, wählen Sie den NFC-Scanner in den Scan-Einstellungen Möchten Sie die Scan-Einstellungen anzeigen?</string>
	<string name="v1_error_nfc_disable_print_title">NFC ist deaktiviert</string>
	<string name="v1_error_nfc_disable_print_msg">Um über NFC zu drucken, aktivieren Sie NFC an Ihrem Mobilgerät.</string>
	<string name="v1_error_nfc_disable_scan_title">NFC ist deaktiviert</string>
	<string name="v1_error_nfc_disable_scan_msg">Um über NFC zu scannen, aktivieren Sie NFC an Ihrem Mobilgerät.</string>
	<string name="v1_error_wrong_settings_duplex_size_title">Falsche Einstellungen</string>
	<string name="v1_error_wrong_settings_duplex_size_msg">Ist die Papiergröße auf „Legal“ eingestellt, schalten Sie den Duplex-Druck aus und versuchen Sie es erneut.</string>
	<string name="v1_error_gcp_printer_not_registered_title">Kein Drucker gefunden</string>
	<string name="v1_error_gcp_printer_not_registered_msg">Sie müssen Ihren Drucker bei Google Cloud Print registrieren. Weitere Informationen erhalten Sie, wenn Sie auf Support tippen, um den Google Cloud Print Guide herunterzuladen und anzuzeigen. </string>
	<string name="v1_error_gcp_printer_offline_title">Drucker offline</string>
	<string name="v1_error_gcp_printer_offline_msg">Prüfen Sie, ob Ihr Brother-Gerät eingeschaltet und mit dem Netzwerk verbunden ist.\nIst „Fortfahren“ ausgewählt, wird der Druckjob auf dem Google Cloud Print-Server gespeichert und gedruckt, wenn der Drucker „online“ geht.</string>
	<string name="v1_generic_item_label_dont_ask_again">Nicht mehr anz.</string>
	<string name="v1_error_gcp_printer_deleted_title">Drucker wurde entfernt</string>
	<string name="v1_error_gcp_printer_deleted_msg">Der gewählte Drucker wurde aus Google Cloud Print entfernt. Anderen Drucker auswählen.</string>
	<string name="v1_error_gcp_cannot_print_title">Druckfehler</string>
	<string name="v1_error_gcp_cannot_print_msg">Dieser Drucker kann nicht ausgewählt werden. Anderen Drucker auswählen.</string>
	<string name="v1_error_scanner_card_top_cover_open_scanning_title">Scannen nicht möglich</string>
	<string name="v1_error_scanner_card_top_cover_open_scanning_msg">Beim Scannen einer Karte obere Abdeckung nicht öffnen.</string>
	<string name="v1_error_scanner_card_top_cover_open_before_scan_title">Scannen nicht möglich</string>
	<string name="v1_error_scanner_card_top_cover_open_before_scan_msg">Obere Abdeckung vor dem Scannen einer Karte schließen.</string>
	<string name="v1_error_scanner_card_slot_insert_title">Scannen nicht möglich</string>
	<string name="v1_error_scanner_card_slot_insert_msg">Während dem Scannen eines Dokuments keine Karte einlegen.</string>
	<string name="v1_error_scanner_card_slot_empty_title">Scannen nicht möglich</string>
	<string name="v1_error_scanner_card_slot_empty_msg">Im Kartenfach befindet sich keine Karte.</string>
	<string name="v1_error_scanner_card_jam_title">Stau der Scandokumente</string>
	<string name="v1_error_scanner_card_jam_msg">Im Kartenfach ist eine Karte eingeklemmt.\nÖffnen Sie die obere/vordere Abdeckung und entfernen Sie die eingeklemmte Karte, indem Sie sie nach hinten ziehen. Versuchen Sie es anschließend erneut.</string>
	<string name="v1_error_nfc_page_not_selected_title">Bedienungsfehler</string>
	<string name="v1_error_nfc_page_not_selected_msg">Keine Druckdaten ausgewählt. Zu druckende Daten auswählen und erneut versuchen.</string>
	<string name="v1_error_gcp_cannot_connect_title">Verbinden nicht möglich</string>
	<string name="v1_error_gcp_cannot_connect_msg">Bestätigen Sie Folgendes:\n-Wenn das Gerät ausgeschaltet ist, schalten Sie es ein. Stellen Sie außerdem sicher, dass die Netzwerkeinstellungen korrekt konfiguriert sind.</string>
	<string name="v1_error_nfc_device_not_supported_title">NFC-Drucker/-Scanner wird nicht unterstützt.</string>
	<string name="v1_error_nfc_device_not_supported_msg">Das Drucken oder Scannen über NFC-Verbindung wird von diesem Brother-Gerät nicht unterstützt.</string>
	<string name="v1_error_widi_connection_failed_title">Keine Verbindung möglich.</string>
	<string name="v1_error_widi_connection_failed_msg">Wi-Fi Direct-Verbindung fehlgeschlagen. Bitte versuchen Sie es erneut.</string>
	<string name="v1_error_service_account_title">Zugriff nicht möglich: %s</string>
	<string name="v1_error_service_account_msg">Prüfen Sie Ihre %s-Kontoeinstellungen und versuchen Sie es erneut.</string>
	<string name="v1_error_service_storage_open_title">Datei aus %s konnte nicht geöffnet werden.</string>
	<string name="v1_error_service_storage_open_msg">Download fehlgeschlagen. Versuchen Sie es erneut.</string>
	<string name="v1_error_local_storage_full_title">Datei aus %s konnte nicht geöffnet werden.</string>
	<string name="v1_error_local_storage_full_msg">Download fehlgeschlagen. Speicher ist voll. Löschen Sie nicht erforderliche Dateien vom Gerät und versuchen Sie es erneut.</string>
	<string name="v1_error_service_data_not_found_title">Datei/Ordner nicht in %s gefunden </string>
	<string name="v1_error_service_data_not_found_msg">Prüfen Sie, ob die Datei/der Ordner in %s vorhanden ist, und versuchen Sie es erneut.</string>
	<string name="v1_error_service_too_many_data_title">Ordner konnte nicht angezeigt werden.</string>
	<string name="v1_error_service_too_many_data_msg">Es gibt zu viele Dateien in diesem Ordner, um die Inhalte anzuzeigen. Löschen Sie alle nicht erforderlichen Dateien und versuchen Sie es erneut. </string>
	<string name="v1_error_service_internal_title">Unbekannter Fehler</string>
	<string name="v1_error_service_internal_msg">Bitte versuchen Sie es erneut.</string>
	<string name="v1_error_service_internet_cannot_connect_title">Keine Internetverbindung</string>
	<string name="v1_error_service_internet_cannot_connect_msg">Überprüfen Sie die Netzwerkeinstellungen.</string>
	<string name="v1_error_service_logout_title">Abmelden von %s konnte nicht ausgeführt werden.</string>
	<string name="v1_error_service_logout_msg">Bitte versuchen Sie es erneut.</string>
	<string name="v1_error_service_limit_title">Anmeldungslimit mit %s überschritten</string>
	<string name="v1_error_service_limit_msg">Bitte warten Sie und versuchen Sie es dann erneut.</string>
	<string name="v1_error_evernote_resource_cannot_download_title">Download nicht möglich </string>
	<string name="v1_error_evernote_resource_cannot_download_msg">Bitte überprüfen Sie die Notiz und versuchen Sie es erneut.</string>
	<string name="v1_error_evernote_rsource_not_found_title">Datei konnte nicht gefunden werden.</string>
	<string name="v1_error_evernote_rsource_not_found_msg">Überprüfen Sie, ob die Datei in Evernote vorhanden ist, und versuchen Sie es erneut.</string>
	<string name="v1_error_evernote_note_cannot_open_title">Notiz kann nicht geöffnet werden.</string>
	<string name="v1_error_evernote_note_cannot_open_msg">Zugriff auf den Inhalt der Notiz nicht möglich. </string>
	<string name="v1_error_evernote_internal_title">Evernote Interner Fehler</string>
	<string name="v1_error_evernote_internal_msg">Bitte warten Sie und versuchen Sie es dann erneut.</string>
	<string name="v1_error_service_not_supported_title">Dieser Service wird nicht unterstützt.</string>
	<string name="v1_error_service_not_supported_msg">Dieser Service wird auf Ihrem Gerät nicht unterstützt.  Sie können diesen Service nicht nutzen.</string>

	<!-- EULA -->
	<string name="v1_generic_btn_Yes">JA</string>
	<string name="v1_generic_btn_No">NEIN</string>
	<string name="v1_generic_title_end_user_lisence_agreement">Endbenutzer-Lizenzvereinbarung für Brother-Software</string>
	<string name="v1_generic_msg_end_user_lisence_agreement">WICHTIG – BITTE AUFMERKSAM LESEN: Diese Endbenutzer-Lizenzvereinbarung (End-User License Agreement, „EULA“) ist eine rechtsgültige Vereinbarung zwischen Ihnen und Brother Industries, Ltd. („Brother“), die Ihre Nutzung der Brother-Software („SOFTWARE“) regelt, welche installiert wird, wenn Sie diese EULA auf dem Bildschirm akzeptieren, nachdem Sie sie gelesen haben.  Falls Sie zustimmen, dass die Bestimmungen dieser EULA für Sie rechtlich bindend sind, dürfen Sie die Software in Übereinstimmung mit den Bestimmungen dieser EULA verwenden.  Wenn Sie den Bestimmungen dieser EULA nicht zustimmen, erhalten Sie keine Lizenz an der SOFTWARE.  In diesem Fall sind Sie nicht berechtigt, die SOFTWARE zu verwenden.\n\n\nBestimmungen.\n\n1. Eigentumsrecht.\nAlle Rechte, Ansprüche und Interessen an der SOFTWARE (einschließlich aller darin enthaltener Urheberrechte und sonstiger geistiger Eigentumsrechte) und an den damit in Zusammenhang stehenden Materialien („Dokumentation“) stehen Brother oder seinen Lieferanten zu.  Die SOFTWARE wird lizenziert, aber nicht verkauft. Außerdem enthält die SOFTWARE verschiedene Open Source-Softwareprogramme („Open Source-Komponenten“). Details zu Open Source-Komponenten finden Sie in den separat definierten Bestimmungen.</string>
	<string name="v1_generic_msg_end_user_lisence_agreement2">2. Lizenzgewährung.\n2.1 Brother gewährt Ihnen eine nicht ausschließliche Lizenz zur Installation und zur Verwendung des Exemplars der SOFTWARE auf Ihren Geräten, in dem Umfang, der für die vorgesehene Verwendung der Produkte von Brother (einschließlich Drucker und Multifunktionsgeräte), für welche die SOFTWARE verwendet werden soll, („Brother-Gerät“) notwendig ist.\n2.2 Des Weiteren gewährt Ihnen Brother eine Lizenz zum Anfertigen einer einzigen Kopie der SOFTWARE ausschließlich zu Archivierungs- und Sicherungszwecken.  Bei jeder solchen Kopie müssen auch alle Hinweise auf Urheberrechte und geistige Eigentumsrechte vom Original reproduziert werden.\n2.3 Über die in den vorstehenden Abschnitten 2.1 und 2.2 ausdrücklich erteilten Genehmigungen und ein eventuell gesetzlich verankertes Recht (das sich rechtmäßig nicht ausschließen lässt) hinaus sind Sie nicht berechtigt, (i) Kopien der SOFTWARE oder der Dokumentation zu erstellen, (ii) die SOFTWARE oder die Dokumentation abzuändern, (iii) die SOFTWARE oder die Dokumentation durch Reverse Engineering zurückzugewinnen, zu disassemblieren, zu dekompilieren oder zur Erstellung von Ableitungen zu verwenden, (iv) die SOFTWARE zu vermieten, zu sublizenzieren, zu übertragen (außer in Übereinstimmung mit Abschnitt 3) oder zu verpachten.\n\n3. Übertragung.\nSie können die SOFTWARE dauerhaft an eine beliebige Person übertragen, sofern Sie beim Übertragen der SOFTWARE an die betreffende Person auch alle Upgrades und die gesamte Dokumentation, die Ihnen von Brother oder in dessen Namen zur Verfügung gestellt wurden, an die betreffende Person übertragen, und unter der Voraussetzung, dass diese Person gegenüber Brother die Zustimmung zu dieser EULA hinsichtlich der jeweiligen Software und Dokumentation bestätigt.  Ungeachtet des zuvor Erwähnten sind Sie nicht berechtigt, dieser Person eine Kopie der SOFTWARE zur Verfügung zu stellen, die Sie gemäß Abschnitt 2.2 angefertigt haben. Bei der Übertragung müssen Sie alle Kopien der SOFTWARE, die Sie angefertigt haben und/oder die auf Geräten vorhanden sind, die sich in Ihrem Besitz oder unter Ihrer Kontrolle befinden, löschen.  Die Garantie ist nicht übertragbar.\n\n4. GARANTIEABLEHNUNG.\nIM GESETZLICH ERLAUBTEN UMFANG WIRD IHNEN DIESE SOFTWARE OHNE MÄNGELGEWÄHR („IM IST-ZUSTAND“) UND OHNE JEGLICHE MÜNDLICH ODER SCHRIFTLICH EXPLIZIT ODER IMPLIZIT FESTGELEGTE GARANTIEN ODER BEDINGUNGEN ZUR VERFÜGUNG GESTELLT. INSBESONDERE LEHNT BROTHER JEGLICHE ART VON IMPLIZITEN GARANTIEN ODER BEDINGUNGEN DER MARKTGÄNGIGKEIT, DER ZUFRIEDENSTELLENDEN QUALITÄT, DER NICHTVERLETZUNG VON RECHTEN UND/ODER DER EIGNUNG FÜR EINEN BESTIMMTEN ZWECK AB.\n\n5. Haftungsbeschränkung.\nAUF KEINEN FALL KANN BROTHER FÜR ENTGANGENEN GEWINN, ENTGANGENE GESCHÄFTSCHANCEN, ENTGANGENE DATENNUTZUNG, UNTERBRECHUNG DER GESCHÄFTSTÄTIGKEIT ODER INDIREKTE, BESONDERE, ZUFÄLLIGE SCHÄDEN, STRAFE ODER SCHADENERSATZ EINSCHLIESSENDE SCHÄDEN ODER FOLGESCHÄDEN HAFTBAR GEMACHT WERDEN, DIE VERTRAGSMÄSSIG, DURCH UNERLAUBTE HANDLUNG ODER AUF SONSTIGE WEISE AUS DER NUTZUNG DIESER SOFTWARE, DER UNFÄHIGKEIT, DIESE ZU NUTZEN, ODER DEM ERGEBNIS DER NUTZUNG DIESER SOFTWARE ENTSTEHEN. DIE NUTZUNG DIESER SOFTWARE ERFOLGT VOLLSTÄNDIG AUF EIGENE GEFAHR. SOLLTE SICH DIE SOFTWARE ALS MÄNGELBEHAFTET ERWEISEN, ÜBERNEHMEN SIE (DER NUTZER) DIE GESAMTEN KOSTEN FÜR ALLE SERVICELEISTUNGEN, REPARATUREN ODER KORREKTUREN UND VERPFLICHTEN SICH IM UMFANG DES ANWENDBAREN RECHTS, BEDINGUNGSLOS AUF ALLE GESETZLICHEN ODER SONSTIGEN RECHTE ZU VERZICHTEN, DIE IHNEN GEGEBENENFALLS BEZÜGLICH SOLCHER MÄNGEL GEGENÜBER BROTHER ZUSTEHEN.\n\n6. Kosten, bei Nutzung dieser SOFTWARE fällige Gebühren\nSie stimmen nach Kenntnisnahme zu, dass Dienste, die durch die SOFTWARE verfügbar sind, durch eine beliebige Netzwerkverbindung und einen beliebigen, von Brother betriebenen Cloud-Server („Server“) bereitgestellt werden können, und daher während der Nutzung dieser SOFTWARE (z.B. Datenumwandlung von PDF zu einem anderen anderen Datenformat) Verbindungsgebühren durch die Nutzung des Netzwerks und Servers entstehen und dass diese Gebühren zu Ihren Lasten gehen.\nZusätzlich zur oben genannten Gebühr sind Sie allein verantwortlich für jegliche Kosten oder Ausgaben, die in Verbindung mit Ihrer Nutzung der SOFTWARE entstehen.\nBrother erstattet in keinem Fall irgendwelche der oben genannten Gebühren, Kosten oder Ausgaben.\n\n7. Drittanbieter-Service\nDie Software nutzt Google Cloud Print von Google Inc. Wenn Sie Google Cloud Print verwenden, müssen Sie sich bei Google Cloud Print über Ihr gültiges Google-Konto anmelden und das Brother-Gerät auf Google Cloud Print registrieren.\nSie müssen den allgemeinen Geschäftsbedingungen von Google Inc. zustimmen und Google Cloud Print gemäß dieser Bestimmungen nutzen.\nSie müssen bestätigen, dass Sie selbst dafür verantwortlich sind, ständig für ausreichend Volumen und Speicherplatz für Ihre Dateien und Daten in Google Cloud Print und anderen Drittanbieterservices und -anwendungen zu sorgen, die Sie mit der SOFTWARE verwenden möchten.  Brother ist in keiner Weise dafür verantwortlich, für entsprechendes Volumen oder entsprechenden Speicherplatz für Ihre Dateien und Daten zu sorgen, auch wenn Sie beim Versuch der Übertragung Ihrer Dateien und Daten an diese Drittanbieterservices oder von diesen Drittanbieterservices nicht über ausreichend Volumen oder Speicherplatz verfügen.\nBrother haftet nicht für jedwede Fehler, Verluste und Schäden, ob sichtbar oder unsichtbar, die Ihnen selbst oder an Ihrem Eigentum in Verbindung mit der SOFTWARE zusammen mit Google Cloud Print und sonstigen Drittanbieterservices und -anwendungen (u. a. Cloud-Speicherdienste wie Dropbox oder OneDrive) entstanden sind, wie u. a. der Verlust von oder Schäden an Dateien und Daten bei dem Versuch eines Uploads oder der Übertragung an einen oder von einem anderen Drittanbieterservice bzw. einer anderen Drittanbieteranwendung, der Verlust von oder Schäden an persönlichen Informationen, die Sie diesen Drittanbietern bereitstellen, oder sonstige Fehler oder Schäden an Ihren Computern, Hardware-Geräten oder anderer von Ihnen verwendeter Software.\n\n8. Verbindung von Software und Brother-Gerät.\nSie nehmen zur Kenntnis, dass Sie bei der Verbindung der SOFTWARE mit dem Brother-Gerät im Online-Zustand ggf. die Einstellungen des Routers ändern und eine eindeutige IP-Adresse, ein gültiges Google-Konto und entsprechende Kennwörter eingeben müssen.  Brother haftet nicht für jedwede Schwierigkeiten, Rechtsstreitigkeiten und Schäden, die beim Versuch der Verbindung der SOFTWARE mit einem Brother-Gerät im Online-Zustand entstehen, das Ihnen oder einer anderen Drittpartei gehört bzw. von Ihnen oder einer anderen Drittpartei verwaltet oder bedient wird.\n\n9. Laufzeit und Kündigung.\nDiese EULA tritt zum Zeitpunkt Ihrer Zustimmung zu ihr in Kraft und bleibt gültig, es sei denn, Sie übertragen die SOFTWARE in Übereinstimmung mit dieser EULA und die übernehmende Person verpflichtet sich gegenüber Brother zur Einhaltung der EULA in Bezug auf die SOFTWARE.\nBrother kann jedoch diese EULA ohne Vorankündigung kündigen, falls Sie gegen eine ihrer Bestimmungen verstoßen.\n\n10. Exportvorschriften.\nSie sind nicht berechtigt, die SOFTWARE oder eine Kopie oder Anpassung davon zu exportieren oder zu reexportieren, falls dies gegen geltendes Recht oder gegen geltende Vorschriften verstößt.\n\n11. Geltendes Recht.\nDiese EULA unterliegt japanischem Recht, und japanische Gerichte haben die ausschließliche Rechtsprechung in Hinblick auf diese EULA außer in Bezug auf die Durchsetzung; bei dieser handelt es sich um eine nicht ausschließliche Rechtsprechung der japanischen Gerichte.\n\n12. Gesetzwidrigkeit.\nFalls Bestimmungen dieser EULA ganz oder teilweise für gesetzwidrig oder nicht durchsetzbar erklärt werden, sind diese Bestimmungen trennbar und unabhängig von den anderen Bestimmungen dieser EULA, und die Gültigkeit der anderen Bestimmungen und der gesamten EULA bleibt davon unberührt.\n\n13. Rechte Dritter.\nDie Bestimmungen dieser EULA sind nur zur Geltung zwischen Brother und Ihnen vorgesehen und nicht dazu gedacht, einer anderen Person einen Vorteil oder ein Durchsetzungsrecht zu gewähren. \n\n14. Persönliche Lizenz.\nDie von Brother im Rahmen dieser Vereinbarung gewährten Rechte gelten für Sie persönlich und Sie sind über die in Abschnitt 3 ausdrücklich erteilten Genehmigungen hinaus nicht berechtigt, die SOFTWARE (oder die Dokumentation) oder die Vorteile und Lasten dieser EULA oder sonstige darin gewährte Rechte einer dritten Person zuzuweisen, zu übertragen oder anderweitig zu überlassen.</string>
	<string name="v1_generic_msg_license_title">Die SOFTWARE enthält die folgende Software (einschließlich, aber nicht beschränkt auf Open-Source-Software). Brother nutzt diese Software in Übereinstimmung mit den im Folgenden aufgeführten Nutzungsbestimmungen.</string>
	<string name="v1_generic_title_gratitude_for_user">Vielen Dank, dass Sie sich für iPrint&amp;Scan entschieden haben. Um die Anwendung weiter zu verbessern, möchten wir regelmäßig anonyme Nutzungsinformationen sammeln. Durch Ihre Zusammenarbeit können wir Ihnen neue Funktionen und ein verbessertes Benutzererlebnis anbieten.</string>
	<string name="v1_generic_btn_privacypolicy">Datenschutzrichtlinie</string>
	<string name="v1_generic_ckbx_ga_title">Informationen senden</string>
	<string name="v1_generic_title_analytics">Brother iPrint&amp;Scan-Datenschutzrichtlinie</string>
	<string name="v1_generic_msg_analytics">Diese Datenschutzrichtlinie regelt Ihre Nutzung der mobilen Anwendung Brother iPrint&amp;Scan („Software“), die von Brother Industries, Ltd. („Brother“ oder „Uns“) bereitgestellt wird. Wenn Sie bestimmte Dateitypen mit der Software drucken möchten, werden diese Dateien automatisch an unseren Server („Server“) gesendet, in druckbare Dateiformate verwandelt und dann an Ihr Mobilgerät zurückgesendet. Sämtliche an den Server gesendete Dateien werden innerhalb kurzer Zeit nach der Konvertierung automatisch gelöscht. Der Server verfügt nicht über Speicherfähigkeit. Außer zum Zweck der Konvertierung speichert oder verwendet Brother keine Dateien ohne Ihre vorherige Zustimmung.\n\nGeräteinformationen und Google Analytics\na) Geräteinformationen\nWenn Sie die Software verwenden, werden ggf. Informationen über Ihr Mobilgerät und Ihren Drucker („Gerät“) oder darüber, wie Sie die Software verwenden (zusammenfassend „Geräteinformationen“), wie Druckermodell, regionale Informationen, Firmware, Verwendung der einzelnen Funktionen der Software, Druckerstatus usw., auf unserem Server gespeichert. Geräteinformationen (außer der Seriennummer) können nicht alleine oder in Kombination mit anderen Informationen, über die wir zur Identifikation Ihrer Person verfügen, verwendet werden. Wir behalten uns das Recht vor, solche Informationen ausschließlich zur Verbesserung der Software oder anderer Produkte/Services von Brother, unserer Marketing-/Forschungsaktivitäten, der Produktplanung oder anderer verbundener Aktivitäten zum Vorteil unserer Kunden (zusammenfassend „Zwecke“) zu verwenden. Wir verwenden Ihre Geräteinformationen ohne Ihr vorheriges Einverständnis nicht für andere Zwecke. Wir geben Ihre Geräteinformationen ggf. anonym und ausschließlich zur Erfüllung der genannten Zwecke an Dritte weiter und verpflichten diese stets dazu, solche Informationen vertraulich zu behandeln.\n\nZu den Geräteinformationen gehört die Seriennummer Ihres Druckers. Die Seriennummer kann mit den Daten in Verbindung gebracht werden, die Sie möglicherweise auf der Website zur Produktregistrierung unserer Vertriebsgesellschaft eingegeben haben. Wir verwenden die Seriennummer jedoch nicht zu Ihrer Identifizierung oder zu anderen als den genannten Zwecken. Die Seriennummer wird möglicherweise in Ländern auf unserem Server gespeichert, in denen das Schutzniveau personenbezogener Daten nicht dem in Ihrem Land entspricht. Jedoch werden wir die Seriennummer unter strenger Einhaltung der „Datenschutzrichtlinien für die Sammlung von Geräteinformationen“ von Brother kontrollieren, die Sie auf der Brother-Website unter  &lt;www.brother.com/rd/privacy/&gt;.\n\nb) Verwendung von Google Analytics\nDie Software nutzt Google Analytics, einen Webanalyse-Service, der von Google, Inc. („Google“) bereitgestellt wird.  Google Analytics erfasst Verbindungsdaten mithilfe von „Cookies“. Die erfassten Daten werden zur Analyse verwendet und helfen uns dabei zu verstehen, wie Sie die Software nutzen. Weitere Informationen zum Umgang von Google mit Ihren Daten finden Sie unter &lt; http://www.google.com/analytics/learn/privacy.html&gt;.\nGoogle und Brother sammeln unter der Verwendung von Google Analytics nicht personenbezogene Daten, wie das von Ihnen verwendete Druckermodell und die Art, wie Sie die Software verwenden und durch die Software navigieren. Brother verwendet diese Informationen ausschließlich für die genannten Zwecke.\n\n</string>
	<string name="v1_generic_msg_analytics_underline">Durch das Bestätigen von \&quot;Informationen senden\&quot; erklären Sie sich mit dem Senden der Geräteinformationen an Brother Server, unter den oben genannten Bedingungen sowie mit der Verwendung von Google Analytics, einverstanden. Wenn Sie den Bedingungen nicht zustimmen, können Sie dennoch die volle Funktionalität der Software nutzen.</string>

</resources>